my_function_dohyun/__init__.py
my_function_dohyun/tool.py
my_function_dohyun-0.0.2.dist-info/METADATA
my_function_dohyun-0.0.2.dist-info/WHEEL
my_function_dohyun-0.0.2.dist-info/top_level.txt
my_function_dohyun-0.0.2.dist-info/RECORD
