Metadata-Version: 2.1
Name: my-function-dohyun
Version: 0.0.2
Summary: A small example package
Author-email: dohyun <author@example.com>
Project-URL: Homepage, https://github.com/pypa/sampleproject
Project-URL: Issues, https://github.com/pypa/sampleproject/issues
Classifier: Programming Language :: Python :: 3
Classifier: License :: OSI Approved :: MIT License
Classifier: Operating System :: OS Independent
Requires-Python: >=3.8
Requires-Dist: openpyxl
Requires-Dist: elasticsearch
Requires-Dist: confluent-kafka
